MANIFEST.in
README.md
setup.py
easy_patents/auth_info.py
easy_patents/convert_case_number.py
easy_patents/delete_caches.py
easy_patents/errors.py
easy_patents/gene_app_number.py
easy_patents/get_apitoken.py
easy_patents/get_info.py
easy_patents/update_authinfo.py
easy_patents.egg-info/PKG-INFO
easy_patents.egg-info/SOURCES.txt
easy_patents.egg-info/dependency_links.txt
easy_patents.egg-info/requires.txt
easy_patents.egg-info/top_level.txt
easy_patents/config/config.ini
easy_patents/sample/mail_notify.py
easy_patents/sample/openai-0.27.4-py3-none-any.whl
easy_patents/sample/sample.py
easy_patents/sample/sample_check_due_date.py
easy_patents/sample/sample_correct_info.py
easy_patents/sample/sample_draft_apeal.py
easy_patents/sample/sample_openai.py
easy_patents/sample/sample_report_oa.py
easy_patents/sample/sample_translate.py
easy_patents/sample/sample_translate_oa.py
easy_patents/sample/sample_update_monitor_excel.py
easy_patents/sample/__pycache__/sample_openai.cpython-39.pyc
easy_patents/sample/__pycache__/sample_translate.cpython-36.pyc
easy_patents/sample/__pycache__/sample_translate.cpython-39.pyc