Metadata-Version: 1.0
Name: easy-patents
Version: 1.0.13
Summary: Utilities for JPO API
Home-page: https://qiita.com/easypatents39/
Author: easypatents39
Author-email: easypatents39@gmail.com
License: MIT
Platform: UNKNOWN
